photography/__init__.py
photography/_cli.py
photography/tests/__init__.py
photography/tests/test_integration.py
photography-2025.6.4.dist-info/METADATA
photography-2025.6.4.dist-info/WHEEL
photography-2025.6.4.dist-info/entry_points.txt
photography-2025.6.4.dist-info/licenses/COPYING
photography-2025.6.4.dist-info/RECORD
