Metadata-Version: 2.4
Name: photography
Version: 2025.6.4
Summary: A CLI for managing a photo library.
Project-URL: Issues, https://github.com/Julian/photography-cli/issues/
Project-URL: Funding, https://github.com/sponsors/Julian
Project-URL: Source, https://github.com/Julian/photography-cli
Author-email: Julian Berman <Julian+photography@GrayVines.com>
License-Expression: MIT
License-File: COPYING
Keywords: images,photography,photos,self-hosting
Classifier: Development Status :: 3 - Alpha
Classifier: Operating System :: OS Independent
Classifier: Programming Language :: Python
Classifier: Programming Language :: Python :: 3
Classifier: Programming Language :: Python :: 3.12
Classifier: Programming Language :: Python :: 3.13
Classifier: Programming Language :: Python :: Implementation :: CPython
Classifier: Programming Language :: Python :: Implementation :: PyPy
Requires-Python: >=3.12
Requires-Dist: attrs
Requires-Dist: imagehash
Requires-Dist: pillow
Requires-Dist: rich-click
Requires-Dist: rpds-py
